maxheap/__init__.py
maxheap/_cmaxheap.c
maxheap/_cmaxheap.cpython-314-x86_64-linux-musl.so
maxheap/_core.py
maxheapx-0.1.1.dist-info/METADATA
maxheapx-0.1.1.dist-info/WHEEL
maxheapx-0.1.1.dist-info/top_level.txt
maxheapx-0.1.1.dist-info/RECORD
