Metadata-Version: 2.4
Name: maxheapx
Version: 0.1.1
Summary: A max-heap library with an API that mirrors Python's heapq (but max-first).
Author: Timothy Roch
License-Expression: MIT
Project-URL: Homepage, https://maxheap.vercel.app
Project-URL: Documentation, https://maxheap.vercel.app/docs
Project-URL: Source, https://github.com/timothyroch/maxheap
Project-URL: Issues, https://github.com/timothyroch/maxheap/issues
Keywords: heap,priority queue,max-heap,data structures
Classifier: Programming Language :: Python :: 3
Classifier: Programming Language :: Python :: 3 :: Only
Classifier: Programming Language :: Python :: 3.9
Classifier: Programming Language :: Python :: 3.10
Classifier: Programming Language :: Python :: 3.11
Classifier: Programming Language :: Python :: 3.12
Classifier: Programming Language :: Python :: 3.13
Classifier: Intended Audience :: Developers
Classifier: Topic :: Software Development :: Libraries
Classifier: Typing :: Typed
Requires-Python: >=3.9
